gammabayes/__init__.py
gammabayes/core/__init__.py
gammabayes/core/binning_geometry.py
gammabayes/core/core_utils.py
gammabayes/core/data_class.py
gammabayes/core/exposure.py
gammabayes/core/gamma_cube.py
gammabayes/core/parameter_class.py
gammabayes/core/parameter_set_class.py
gammabayes/core/parameter_set_collection_class.py
gammabayes/core/utils.py
gammabayes/dark_matter/__init__.py
gammabayes/dark_matter/combined_DM_class.py
gammabayes/dark_matter/custom_ratios_model.py
gammabayes/dark_matter/channel_spectra/__init__.py
gammabayes/dark_matter/channel_spectra/PPPC_Tables/AtProduction_gamma_EW_corrections.dat
gammabayes/dark_matter/channel_spectra/PPPC_Tables/PPPC_reader.py
gammabayes/dark_matter/channel_spectra/PPPC_Tables/__init__.py
gammabayes/dark_matter/channel_spectra/griddata/__init__.py
gammabayes/dark_matter/channel_spectra/single_channel_spectral_model/__init__.py
gammabayes/dark_matter/channel_spectra/single_channel_spectral_model/single_channel_DM_Spectral_Class.py
gammabayes/dark_matter/density_profiles/DM_Profiles.py
gammabayes/dark_matter/density_profiles/__init__.py
gammabayes/dark_matter/density_profiles/base_dm_profile.py
gammabayes/dark_matter/density_profiles/gammapy_wrappers.py
gammabayes/dark_matter/spectral_models/__init__.py
gammabayes/dark_matter/spectral_models/Z2_ScalarSinglet/SS_DM_Spectral_Class.py
gammabayes/dark_matter/spectral_models/Z2_ScalarSinglet/__init__.py
gammabayes/dark_matter/spectral_models/Z2_ScalarSinglet/annihilation_ratio_data/__init__.py
gammabayes/dark_matter/spectral_models/Z2_ScalarSinglet/annihilation_ratio_data/annihilation_ratios__darkSUSY.csv
gammabayes/dark_matter/spectral_models/Z2_ScalarSinglet/annihilation_ratio_data/annihilation_ratios__dimauromattia.csv
gammabayes/dark_matter/spectral_models/Z2_ScalarSinglet/temp/__init__.py
gammabayes/dark_matter/spectral_models/Z5/Z5_spectral_class.py
gammabayes/dark_matter/spectral_models/Z5/__init__.py
GammaBayes-0.1.9.dist-info/LICENSE
GammaBayes-0.1.9.dist-info/METADATA
GammaBayes-0.1.9.dist-info/WHEEL
GammaBayes-0.1.9.dist-info/top_level.txt
GammaBayes-0.1.9.dist-info/RECORD
