Metadata-Version: 2.1
Name: GammaBayes
Version: 0.1.9
Summary: A package for Bayesian dark matter inference
Home-page: https://github.com/lpin0002/GammaBayes
Author: Liam Pinchbeck
Author-email: Liam.Pinchbeck@monash.edu
License: MIT
Classifier: License :: OSI Approved :: MIT License
Classifier: Operating System :: Unix
Requires-Python: >=3.6
License-File: LICENSE
Requires-Dist: astropy ==5.3.4
Requires-Dist: corner >=2.2.2
Requires-Dist: dynesty ==2.1.2
Requires-Dist: jupyterlab >=3.6.3
Requires-Dist: matplotlib >=3.7.1
Requires-Dist: scipy ==1.11.3
Requires-Dist: tqdm >=4.65.0
Requires-Dist: numpy >=1.23
Requires-Dist: gammapy ==1.1
Requires-Dist: pandas >=1.5.3
Requires-Dist: healpy
Requires-Dist: pytest
Requires-Dist: h5py
Requires-Dist: icecream
Requires-Dist: seaborn
